tudu_cli/__init__.py
tudu_cli-0.1.0.dist-info/WHEEL
tudu_cli-0.1.0.dist-info/METADATA
tudu_cli-0.1.0.dist-info/RECORD
