Metadata-Version: 2.1
Name: tudu-cli
Version: 0.1.0
Summary: 
Author: Tom Dugan
Author-email: tom@dugan.email
Requires-Python: >=3.7,<4.0
Classifier: Programming Language :: Python :: 3
Classifier: Programming Language :: Python :: 3.7
Classifier: Programming Language :: Python :: 3.8
Requires-Dist: click (>=7.1.2,<8.0.0)
Requires-Dist: todoist-python (>=8.1.1,<9.0.0)
